thermoengine/__init__.py
thermoengine/calibrate.py
thermoengine/chem_library.py
thermoengine/chemistry.py
thermoengine/coder.py
thermoengine/const.py
thermoengine/core.py
thermoengine/equilibrate.py
thermoengine/model.py
thermoengine/phases.py
thermoengine/redox.py
thermoengine/samples.py
thermoengine/sulfide_liquid.py
thermoengine/data/__init__.py
thermoengine/data/databases/BermanPurePhases.csv
thermoengine/data/databases/BermanSolutionPhases.csv
thermoengine/data/databases/GeoSysComps.csv
thermoengine/data/databases/HollandAndPowellPurePhases.csv
thermoengine/data/databases/HollandAndPowellPurePhasesOriginal.csv
thermoengine/data/databases/HollandAndPowellSolutionPhases.csv
thermoengine/data/databases/StixrudePurePhases.csv
thermoengine/data/databases/StixrudeSolutionPhases.csv
thermoengine/data/databases/__init__.py
thermoengine/data/phases/LEPR-phases.csv
thermoengine/data/phases/Phase-Abbrev-List.csv
thermoengine/data/phases/PurePhaseList.csv
thermoengine/data/phases/SolutionPhaseList.csv
thermoengine/data/phases/__init__.py
thermoengine/magmaforge/__init__.py
thermoengine/magmaforge/plot.py
thermoengine/magmaforge/state_info.py
thermoengine/magmaforge/system.py
thermoengine/magmaforge/system_calculator.py
thermoengine/phase_library/__init__.py
thermoengine/phase_library/MELTS/Clinopyroxene_SG94.cpython-310-x86_64-linux-gnu.so
thermoengine/phase_library/MELTS/Feldspar_EG90.cpython-310-x86_64-linux-gnu.so
thermoengine/phase_library/MELTS/Feldspar_EG90_rhyoliteMELTS.cpython-310-x86_64-linux-gnu.so
thermoengine/phase_library/MELTS/Fluid_DZ06.cpython-310-x86_64-linux-gnu.so
thermoengine/phase_library/MELTS/Garnet_BK91.cpython-310-x86_64-linux-gnu.so
thermoengine/phase_library/MELTS/Liquid_v1_0.cpython-310-x86_64-linux-gnu.so
thermoengine/phase_library/MELTS/Liquid_v1_2.cpython-310-x86_64-linux-gnu.so
thermoengine/phase_library/MELTS/Liquid_v2_0.cpython-310-x86_64-linux-gnu.so
thermoengine-1.5.5.dist-info/METADATA
thermoengine-1.5.5.dist-info/WHEEL
thermoengine-1.5.5.dist-info/top_level.txt
thermoengine-1.5.5.dist-info/RECORD
thermoengine-1.5.5.dist-info/licenses/LICENSE
