Metadata-Version: 2.4
Name: thermoengine
Version: 1.5.5
Summary: Foundational Python package for ENKI thermodynamics modeling
Author-email: "Aaron S. Wolf" <aswolf@seti.org>, "Mark S. Ghiorso" <ghiorso@ofm-research.org>, "Simon W. Matthews" <simonm@hi.is>
License:                     GNU AFFERO GENERAL PUBLIC LICENSE
Project-URL: Homepage, https://gitlab.com/ENKI-portal/ThermoEngine
Project-URL: Bug Tracker, https://gitlab.com/ENKI-portal/ThermoEngine/-/issues/new
Classifier: Development Status :: 4 - Beta
Classifier: Environment :: Plugins
Classifier: Intended Audience :: Developers
Classifier: Intended Audience :: Education
Classifier: Intended Audience :: Science/Research
Classifier: License :: OSI Approved :: GNU Affero General Public License v3
Classifier: Natural Language :: English
Classifier: Operating System :: OS Independent
Classifier: Programming Language :: Python
Classifier: Topic :: Scientific/Engineering
Classifier: Topic :: Scientific/Engineering :: Chemistry
Classifier: Topic :: Scientific/Engineering :: Mathematics
Classifier: Topic :: Scientific/Engineering :: Physics
Classifier: Topic :: Software Development :: Libraries :: Python Modules
Requires-Python: <3.11,>=3.10
License-File: LICENSE
Requires-Dist: cython
Requires-Dist: arrow>=1.2.3
Requires-Dist: cmake>=3.25.0
Requires-Dist: coverage>=7.0.0
Requires-Dist: deprecation>=2.1.0
Requires-Dist: isoduration>=20.11.0
Requires-Dist: jsonpointer>=2.0
Requires-Dist: matplotlib>=3.6.2
Requires-Dist: nptyping
Requires-Dist: numdifftools
Requires-Dist: openpyxl
Requires-Dist: pandas>=1.5.2
Requires-Dist: pytest>=7.2.0
Requires-Dist: pytest-cov>=4.0.0
Requires-Dist: scipy>=1.9.3
Requires-Dist: seaborn>=0.12.1
Requires-Dist: statsmodels
Requires-Dist: sympy>=1.11.1
Requires-Dist: thermoengine-utils
Dynamic: license-file
